{
   "name": "Temple of Madness",
   "code": "ddia-mord",
   "entity": "Scene",
   "id": "scenes/ddia-mord-scene-1",
   "type": "scene",
   "flags": {
      "vtta": {
         "folders": [
            "02 Section 2. Temple of Madness"
         ]
      }
   },
   "grid": {
      "units": "ft",
      "distance": 5,
      "type": 1,
      "value": 50
   },
   "img": {
      "height": 1734,
      "shift": {
         "x": 0,
         "y": 0
      },
      "width": 1301
   },
   "journals": [
      {
         "id": "journals/ddia-mord-scene-1-11",
         "positions": [
         ]
      },
      {
         "id": "journals/ddia-mord-scene-1-10",
         "positions": [
         ]
      },
      {
         "id": "journals/ddia-mord-scene-1-09",
         "positions": [
         ]
      },
      {
         "id": "journals/ddia-mord-scene-1-08",
         "positions": [
         ]
      },
      {
         "id": "journals/ddia-mord-scene-1-07",
         "positions": [
         ]
      },
      {
         "id": "journals/ddia-mord-scene-1-06",
         "positions": [
         ]
      },
      {
         "id": "journals/ddia-mord-scene-1-05",
         "positions": [
         ]
      },
      {
         "id": "journals/ddia-mord-scene-1-04",
         "positions": [
         ]
      },
      {
         "id": "journals/ddia-mord-scene-1-03",
         "positions": [
         ]
      },
      {
         "id": "journals/ddia-mord-scene-1-02",
         "positions": [
         ]
      },
      {
         "id": "journals/ddia-mord-scene-1-01",
         "positions": [
         ]
      }
   ],
   "monsters": [
   ],
   "walls": [
   ]
}