{
   "id": "scenes/cm-scene-8.1",
   "name": "Grippli Village",
   "code": "cm",
   "entity": "Scene",
   "flags": {
      "vtta": {
         "folders": [
            "08 Book of Cylinders"
         ]
      }
   },
   "grid": {
      "distance": 5,
      "type": 1,
      "units": "ft",
      "value": 50
   },
   "img": {
      "height": 2134,
      "shift": {
         "x": 0,
         "y": 0
      },
      "width": 3000
   },
   "journals": [
      {
         "id": "journals/cm-scene-8.1-04",
         "positions": [
         ]
      },
      {
         "id": "journals/cm-scene-8.1-03",
         "positions": [
         ]
      },
      {
         "id": "journals/cm-scene-8.1-02",
         "positions": [
         ]
      },
      {
         "id": "journals/cm-scene-8.1-01",
         "positions": [
         ]
      }
   ],
   "monsters": [
   ],
   "type": "scene"
}