{
   "id": "scenes/lmop-scene-2.2",
   "name": "Redbrand Hideout",
   "backgroundColor": "#575342",
   "code": "lmop",
   "entity": "Scene",
   "flags": {
      "vtta": {
         "folders": [
            "02 Part 2: Phandalin"
         ]
      }
   },
   "grid": {
      "distance": 5,
      "type": 1,
      "units": "ft",
      "value": 150
   },
   "img": {
      "height": 3145,
      "shift": {
         "x": -143,
         "y": -155
      },
      "width": 4508
   },
   "journals": [
      {
         "id": "journals/lmop-scene-2.2-12",
         "positions": [
            {
               "x": 2475,
               "y": 1725
            }
         ]
      },
      {
         "id": "journals/lmop-scene-2.2-11",
         "positions": [
            {
               "x": 2025,
               "y": 1725
            }
         ]
      },
      {
         "id": "journals/lmop-scene-2.2-10",
         "positions": [
            {
               "x": 2025,
               "y": 2625
            }
         ]
      },
      {
         "id": "journals/lmop-scene-2.2-09",
         "positions": [
            {
               "x": 2025,
               "y": 3675
            }
         ]
      },
      {
         "id": "journals/lmop-scene-2.2-08",
         "positions": [
            {
               "x": 2775,
               "y": 2925
            }
         ]
      },
      {
         "id": "journals/lmop-scene-2.2-07",
         "positions": [
            {
               "x": 3292.6470588235293,
               "y": 1804.4117647058824
            }
         ]
      },
      {
         "id": "journals/lmop-scene-2.2-06",
         "positions": [
            {
               "x": 4048.5294117647063,
               "y": 1727.9411764705883
            }
         ]
      },
      {
         "id": "journals/lmop-scene-2.2-05",
         "positions": [
            {
               "x": 4575,
               "y": 2025
            }
         ]
      },
      {
         "id": "journals/lmop-scene-2.2-04",
         "positions": [
            {
               "x": 4125,
               "y": 2475
            }
         ]
      },
      {
         "id": "journals/lmop-scene-2.2-03",
         "positions": [
            {
               "x": 5325,
               "y": 2775
            }
         ]
      },
      {
         "id": "journals/lmop-scene-2.2-02",
         "positions": [
            {
               "x": 3975,
               "y": 3225
            }
         ]
      },
      {
         "id": "journals/lmop-scene-2.2-01",
         "positions": [
            {
               "x": 5033.823529411764,
               "y": 3454.4117647058824
            }
         ]
      }
   ],
   "lights": [
   ],
   "monsters": [
   ],
   "type": "scene",
   "walls": [
      {
         "c": [
            1641,
            1500,
            1650,
            2100
         ]
      },
      {
         "c": [
            1650,
            2100,
            1959,
            2100
         ]
      },
      {
         "c": [
            1959,
            2100,
            2100,
            2100
         ],
         "door": 1
      },
      {
         "c": [
            2100,
            2100,
            2250,
            2100
         ]
      },
      {
         "c": [
            2250,
            2100,
            2250,
            1800
         ]
      },
      {
         "c": [
            2250,
            1800,
            2250,
            1659
         ],
         "door": 1
      },
      {
         "c": [
            2250,
            1659,
            2250,
            1500
         ]
      },
      {
         "c": [
            1641,
            1500,
            4200,
            1500
         ]
      },
      {
         "c": [
            4200,
            1500,
            4200,
            1950
         ]
      },
      {
         "c": [
            4350,
            1950,
            3891,
            1950
         ]
      },
      {
         "c": [
            3900,
            1950,
            3750,
            1950
         ],
         "door": 1
      },
      {
         "c": [
            3750,
            1950,
            3750,
            1650
         ]
      },
      {
         "c": [
            3900,
            1500,
            3900,
            1650
         ],
         "door": 1,
         "ds": 2
      },
      {
         "c": [
            3900,
            1650,
            3900,
            1950
         ]
      },
      {
         "c": [
            4350,
            1950,
            4350,
            1500
         ]
      },
      {
         "c": [
            4350,
            1500,
            4800,
            1500
         ]
      },
      {
         "c": [
            4800,
            1500,
            4800,
            2550
         ]
      },
      {
         "c": [
            4350,
            1950,
            4350,
            2100
         ],
         "door": 1
      },
      {
         "c": [
            4350,
            2100,
            4350,
            2550
         ]
      },
      {
         "c": [
            4350,
            2550,
            5550,
            2550
         ]
      },
      {
         "c": [
            5550,
            2550,
            5550,
            2850
         ]
      },
      {
         "c": [
            5550,
            2850,
            5400,
            2850
         ]
      },
      {
         "c": [
            5400,
            2850,
            5400,
            3000
         ]
      },
      {
         "c": [
            5250,
            3000,
            5250,
            2850
         ]
      },
      {
         "c": [
            5250,
            2850,
            3750,
            2850
         ]
      },
      {
         "c": [
            4350,
            2550,
            4350,
            2850
         ],
         "door": 1
      },
      {
         "c": [
            3750,
            1950,
            3750,
            2850
         ]
      },
      {
         "c": [
            3750,
            3000,
            4200,
            3000
         ]
      },
      {
         "c": [
            4200,
            3000,
            4200,
            3150
         ]
      },
      {
         "c": [
            4200,
            3150,
            4350,
            3150
         ]
      },
      {
         "c": [
            4350,
            3150,
            4350,
            3000
         ]
      },
      {
         "c": [
            4350,
            3000,
            4800,
            3000
         ]
      },
      {
         "c": [
            4800,
            3000,
            4800,
            3150
         ]
      },
      {
         "c": [
            4800,
            3150,
            5100,
            3150
         ]
      },
      {
         "c": [
            5100,
            3150,
            5100,
            3000
         ]
      },
      {
         "c": [
            5100,
            3000,
            5250,
            3000
         ]
      },
      {
         "c": [
            5550,
            3000,
            5550,
            3300
         ]
      },
      {
         "c": [
            5550,
            3300,
            5550,
            3450
         ],
         "door": 1
      },
      {
         "c": [
            5550,
            3450,
            5550,
            3900
         ]
      },
      {
         "c": [
            5550,
            3900,
            5100,
            3900
         ]
      },
      {
         "c": [
            5100,
            3900,
            5100,
            3750
         ]
      },
      {
         "c": [
            5100,
            3750,
            4800,
            3750
         ]
      },
      {
         "c": [
            4800,
            3750,
            4800,
            3900
         ]
      },
      {
         "c": [
            4800,
            3900,
            4359,
            3900
         ]
      },
      {
         "c": [
            4359,
            3750,
            4359,
            3300
         ]
      },
      {
         "c": [
            4350,
            3300,
            4350,
            3150
         ],
         "door": 1
      },
      {
         "c": [
            5250,
            3750,
            5400,
            3750
         ]
      },
      {
         "c": [
            5400,
            3750,
            5400,
            3150
         ]
      },
      {
         "c": [
            5400,
            3150,
            5250,
            3150
         ],
         "door": 1
      },
      {
         "c": [
            4359,
            3750,
            3750,
            3750
         ]
      },
      {
         "c": [
            3750,
            3750,
            3750,
            3609
         ]
      },
      {
         "c": [
            3750,
            3450,
            3450,
            3450
         ]
      },
      {
         "c": [
            3450,
            3450,
            3450,
            3375
         ]
      },
      {
         "c": [
            3450,
            3375,
            3469,
            3338
         ]
      },
      {
         "c": [
            3469,
            3338,
            3450,
            3244
         ]
      },
      {
         "c": [
            3450,
            3244,
            3422,
            3188
         ]
      },
      {
         "c": [
            3422,
            3188,
            3366,
            3169
         ]
      },
      {
         "c": [
            3366,
            3169,
            3403,
            3113
         ]
      },
      {
         "c": [
            3403,
            3113,
            3384,
            3028
         ]
      },
      {
         "c": [
            3384,
            3028,
            3328,
            2953
         ]
      },
      {
         "c": [
            3328,
            2953,
            3328,
            2850
         ]
      },
      {
         "c": [
            3328,
            2850,
            3384,
            2794
         ]
      },
      {
         "c": [
            3384,
            2794,
            3384,
            2756
         ]
      },
      {
         "c": [
            3384,
            2756,
            3478,
            2681
         ]
      },
      {
         "c": [
            3478,
            2681,
            3469,
            2634
         ]
      },
      {
         "c": [
            3469,
            2634,
            3619,
            2513
         ]
      },
      {
         "c": [
            3619,
            2513,
            3600,
            2419
         ]
      },
      {
         "c": [
            3600,
            2419,
            3638,
            2316
         ]
      },
      {
         "c": [
            3638,
            2316,
            3638,
            2250
         ]
      },
      {
         "c": [
            3638,
            2250,
            3656,
            2138
         ]
      },
      {
         "c": [
            3656,
            2138,
            3563,
            2063
         ]
      },
      {
         "c": [
            3563,
            2063,
            3450,
            2006
         ]
      },
      {
         "c": [
            3450,
            2006,
            3450,
            1959
         ]
      },
      {
         "c": [
            3450,
            1959,
            3600,
            1959
         ]
      },
      {
         "c": [
            3600,
            1959,
            3600,
            1650
         ]
      },
      {
         "c": [
            3600,
            1650,
            3731,
            1650
         ]
      },
      {
         "c": [
            3731,
            1650,
            3731,
            1500
         ],
         "door": 2
      },
      {
         "c": [
            4331,
            3750,
            4331,
            3900
         ],
         "door": 2
      },
      {
         "c": [
            4331,
            3900,
            3600,
            3900
         ]
      },
      {
         "c": [
            3600,
            3900,
            3600,
            3600
         ]
      },
      {
         "c": [
            3600,
            3600,
            3338,
            3600
         ]
      },
      {
         "c": [
            3338,
            3600,
            3319,
            3675
         ]
      },
      {
         "c": [
            3300,
            3740,
            3253,
            3759
         ]
      },
      {
         "c": [
            3253,
            3759,
            3150,
            3759
         ]
      },
      {
         "c": [
            3150,
            3759,
            3113,
            3647
         ]
      },
      {
         "c": [
            3113,
            3647,
            3028,
            3675
         ]
      },
      {
         "c": [
            3028,
            3675,
            3009,
            3750
         ]
      },
      {
         "c": [
            3009,
            3750,
            3028,
            3844
         ]
      },
      {
         "c": [
            3028,
            3844,
            3009,
            3909
         ]
      },
      {
         "c": [
            3009,
            3909,
            3009,
            3984
         ]
      },
      {
         "c": [
            3009,
            3984,
            3000,
            4050
         ]
      },
      {
         "c": [
            2841,
            4050,
            2831,
            3966
         ]
      },
      {
         "c": [
            2831,
            3966,
            2850,
            3919
         ]
      },
      {
         "c": [
            2850,
            3919,
            2803,
            3853
         ]
      },
      {
         "c": [
            2803,
            3853,
            2803,
            3844
         ]
      },
      {
         "c": [
            2803,
            3853,
            2841,
            3769
         ]
      },
      {
         "c": [
            2841,
            3769,
            2803,
            3647
         ]
      },
      {
         "c": [
            2803,
            3647,
            2719,
            3609
         ]
      },
      {
         "c": [
            2719,
            3609,
            2625,
            3609
         ]
      },
      {
         "c": [
            2625,
            3609,
            2578,
            3600
         ]
      },
      {
         "c": [
            2578,
            3600,
            2494,
            3478
         ]
      },
      {
         "c": [
            2494,
            3478,
            2400,
            3450
         ]
      },
      {
         "c": [
            2400,
            3450,
            2400,
            3900
         ]
      },
      {
         "c": [
            2400,
            3900,
            1650,
            3900
         ]
      },
      {
         "c": [
            1650,
            3900,
            1650,
            3450
         ]
      },
      {
         "c": [
            1650,
            3450,
            1800,
            3450
         ]
      },
      {
         "c": [
            1800,
            3450,
            1950,
            3450
         ],
         "door": 1
      },
      {
         "c": [
            1950,
            3450,
            2400,
            3450
         ]
      },
      {
         "c": [
            1800,
            3450,
            1800,
            3000
         ]
      },
      {
         "c": [
            1800,
            3000,
            1650,
            3000
         ]
      },
      {
         "c": [
            1650,
            3000,
            1650,
            2250
         ]
      },
      {
         "c": [
            1650,
            2250,
            1950,
            2250
         ]
      },
      {
         "c": [
            1950,
            2250,
            2100,
            2250
         ],
         "door": 1
      },
      {
         "c": [
            2100,
            2250,
            2400,
            2250
         ]
      },
      {
         "c": [
            2400,
            2250,
            2400,
            3000
         ]
      },
      {
         "c": [
            2400,
            3000,
            1950,
            3000
         ]
      },
      {
         "c": [
            1950,
            3000,
            1800,
            3000
         ],
         "door": 1
      },
      {
         "c": [
            2400,
            2250,
            2550,
            2250
         ]
      },
      {
         "c": [
            2550,
            2250,
            2550,
            2400
         ]
      },
      {
         "c": [
            2550,
            2400,
            2831,
            2400
         ]
      },
      {
         "c": [
            2831,
            2400,
            2813,
            2456
         ]
      },
      {
         "c": [
            2813,
            2456,
            2794,
            2513
         ]
      },
      {
         "c": [
            2794,
            2513,
            2794,
            2597
         ]
      },
      {
         "c": [
            2794,
            2597,
            2728,
            2691
         ]
      },
      {
         "c": [
            2728,
            2691,
            2719,
            2691
         ]
      },
      {
         "c": [
            2728,
            2691,
            2672,
            2766
         ]
      },
      {
         "c": [
            2672,
            2766,
            2625,
            2813
         ]
      },
      {
         "c": [
            2625,
            2813,
            2541,
            2850
         ]
      },
      {
         "c": [
            2541,
            2850,
            2522,
            2963
         ]
      },
      {
         "c": [
            2522,
            2963,
            2503,
            3038
         ]
      },
      {
         "c": [
            2503,
            3038,
            2522,
            3094
         ]
      },
      {
         "c": [
            2522,
            3094,
            2503,
            3206
         ]
      },
      {
         "c": [
            2503,
            3206,
            2466,
            3300
         ]
      },
      {
         "c": [
            2466,
            3300,
            1950,
            3300
         ]
      },
      {
         "c": [
            1950,
            3300,
            1950,
            3000
         ]
      },
      {
         "c": [
            2250,
            1950,
            2841,
            1950
         ]
      },
      {
         "c": [
            2841,
            1950,
            2841,
            1650
         ]
      },
      {
         "c": [
            2859,
            1650,
            2859,
            1950
         ]
      },
      {
         "c": [
            2859,
            1950,
            2991,
            1950
         ]
      },
      {
         "c": [
            2991,
            1800,
            2991,
            1500
         ]
      },
      {
         "c": [
            3009,
            1500,
            3009,
            1800
         ]
      },
      {
         "c": [
            3009,
            1950,
            3150,
            1950
         ]
      },
      {
         "c": [
            3150,
            1950,
            3113,
            2006
         ]
      },
      {
         "c": [
            3113,
            2006,
            3094,
            2072
         ]
      },
      {
         "c": [
            3094,
            2072,
            3038,
            2128
         ]
      },
      {
         "c": [
            3038,
            2128,
            2972,
            2109
         ]
      },
      {
         "c": [
            2972,
            2109,
            2888,
            2109
         ]
      },
      {
         "c": [
            2888,
            2109,
            2869,
            2166
         ]
      },
      {
         "c": [
            2869,
            2166,
            2784,
            2213
         ]
      },
      {
         "c": [
            2784,
            2213,
            2719,
            2203
         ]
      },
      {
         "c": [
            2719,
            2203,
            2700,
            2100
         ]
      },
      {
         "c": [
            2700,
            2100,
            2250,
            2100
         ]
      },
      {
         "c": [
            4350,
            1800,
            4500,
            1800
         ],
         "sense": 0
      },
      {
         "c": [
            4650,
            1800,
            4800,
            1800
         ],
         "sense": 0
      },
      {
         "c": [
            4650,
            2250,
            4800,
            2250
         ],
         "sense": 0
      },
      {
         "c": [
            4500,
            2250,
            4350,
            2250
         ],
         "sense": 0
      },
      {
         "c": [
            4500,
            2250,
            4650,
            2250
         ],
         "door": 1,
         "ds": 2
      },
      {
         "c": [
            4500,
            1800,
            4650,
            1800
         ],
         "door": 1,
         "ds": 2
      },
      {
         "c": [
            5400,
            3000,
            5550,
            3000
         ]
      },
      {
         "c": [
            5400,
            3000,
            5250,
            3000
         ],
         "door": 2,
         "ds": 1
      },
      {
         "c": [
            4359,
            3750,
            4359,
            3900
         ],
         "door": 2
      },
      {
         "c": [
            2859,
            1650,
            2859,
            1500
         ],
         "door": 2
      },
      {
         "c": [
            2841,
            1650,
            2841,
            1500
         ],
         "door": 2
      },
      {
         "c": [
            2991,
            1800,
            2991,
            1950
         ],
         "door": 2
      },
      {
         "c": [
            3009,
            1800,
            3009,
            1950
         ],
         "door": 2
      },
      {
         "c": [
            3750,
            1650,
            3750,
            1500
         ],
         "door": 2
      },
      {
         "c": [
            3750,
            3000,
            3750,
            3450
         ]
      },
      {
         "c": [
            2841,
            4050,
            3000,
            4050
         ]
      },
      {
         "c": [
            4359,
            3300,
            4200,
            3300
         ]
      },
      {
         "c": [
            4200,
            3300,
            4200,
            3609
         ]
      },
      {
         "c": [
            4200,
            3609,
            3750,
            3609
         ]
      },
      {
         "c": [
            3750,
            3609,
            3750,
            3450
         ]
      },
      {
         "c": [
            5550,
            3450,
            5700,
            3450
         ]
      },
      {
         "c": [
            5700,
            3450,
            5700,
            3300
         ]
      },
      {
         "c": [
            5700,
            3300,
            5550,
            3300
         ]
      },
      {
         "c": [
            3009,
            1800,
            2990,
            1800
         ]
      },
      {
         "c": [
            3009,
            1950,
            2990,
            1950
         ]
      },
      {
         "c": [
            2859,
            1650,
            2840,
            1650
         ]
      },
      {
         "c": [
            3206,
            2550,
            3262,
            2568
         ]
      },
      {
         "c": [
            3262,
            2568,
            3290,
            2615
         ]
      },
      {
         "c": [
            3290,
            2615,
            3262,
            2681
         ]
      },
      {
         "c": [
            3262,
            2681,
            3196,
            2671
         ]
      },
      {
         "c": [
            3196,
            2671,
            3178,
            2615
         ]
      },
      {
         "c": [
            3178,
            2615,
            3206,
            2550
         ]
      },
      {
         "c": [
            2756,
            3159,
            2803,
            3187
         ]
      },
      {
         "c": [
            2803,
            3187,
            2812,
            3215
         ]
      },
      {
         "c": [
            2812,
            3215,
            2840,
            3225
         ]
      },
      {
         "c": [
            2840,
            3225,
            2840,
            3262
         ]
      },
      {
         "c": [
            2840,
            3262,
            2793,
            3290
         ]
      },
      {
         "c": [
            2793,
            3290,
            2746,
            3300
         ]
      },
      {
         "c": [
            2746,
            3300,
            2728,
            3281
         ]
      },
      {
         "c": [
            2728,
            3281,
            2728,
            3234
         ]
      },
      {
         "c": [
            2728,
            3234,
            2718,
            3187
         ]
      },
      {
         "c": [
            2718,
            3187,
            2756,
            3159
         ]
      },
      {
         "c": [
            3731,
            1650,
            3750,
            1650
         ]
      },
      {
         "c": [
            3300,
            3740,
            3318,
            3675
         ]
      },
      {
         "c": [
            4331,
            3900,
            4359,
            3900
         ]
      }
   ]
}